finvista/__init__.py
finvista/_version.py
finvista/py.typed
finvista/_core/__init__.py
finvista/_core/config.py
finvista/_core/exceptions.py
finvista/_core/types.py
finvista/_fetchers/__init__.py
finvista/_fetchers/cache.py
finvista/_fetchers/circuit_breaker.py
finvista/_fetchers/http_client.py
finvista/_fetchers/rate_limiter.py
finvista/_fetchers/source_manager.py
finvista/_fetchers/adapters/__init__.py
finvista/_fetchers/adapters/base.py
finvista/_fetchers/adapters/eastmoney.py
finvista/_fetchers/adapters/legulegu.py
finvista/_fetchers/adapters/registry.py
finvista/_fetchers/adapters/shenwan.py
finvista/_fetchers/adapters/sina.py
finvista/_fetchers/adapters/tencent.py
finvista/_fetchers/adapters/tiantian.py
finvista/_fetchers/adapters/yahoo.py
finvista/_services/__init__.py
finvista/alternative/__init__.py
finvista/cli/__init__.py
finvista/cli/main.py
finvista/fundamental/__init__.py
finvista/macro/__init__.py
finvista/macro/china.py
finvista/markets/__init__.py
finvista/markets/china/__init__.py
finvista/markets/china/convertible.py
finvista/markets/china/etf.py
finvista/markets/china/financial.py
finvista/markets/china/fund.py
finvista/markets/china/futures.py
finvista/markets/china/index.py
finvista/markets/china/industry.py
finvista/markets/china/lhb.py
finvista/markets/china/minute.py
finvista/markets/china/moneyflow.py
finvista/markets/china/option.py
finvista/markets/china/shareholder.py
finvista/markets/china/stock.py
finvista/markets/china/valuation.py
finvista/markets/global_/__init__.py
finvista/markets/global_/forex.py
finvista/markets/hk/__init__.py
finvista/markets/hk/index.py
finvista/markets/us/__init__.py
finvista/markets/us/index.py
finvista/markets/us/stock.py
finvista/utils/__init__.py
finvista-1.0.0.dist-info/METADATA
finvista-1.0.0.dist-info/WHEEL
finvista-1.0.0.dist-info/entry_points.txt
finvista-1.0.0.dist-info/licenses/LICENSE
finvista-1.0.0.dist-info/RECORD
