Metadata-Version: 2.4
Name: finvista
Version: 1.0.0
Summary: A powerful Python library for global financial data with multi-source failover
Project-URL: Homepage, https://github.com/finvfamily/finvista
Project-URL: Documentation, https://github.com/finvfamily/finvista#readme
Project-URL: Repository, https://github.com/finvfamily/finvista
Project-URL: Changelog, https://github.com/finvfamily/finvista/releases
Author: FinVista Contributors
License-Expression: MIT
License-File: LICENSE
Keywords: data,finance,investment,market,pandas,quantitative,stock,trading
Classifier: Development Status :: 4 - Beta
Classifier: Intended Audience :: Developers
Classifier: Intended Audience :: Financial and Insurance Industry
Classifier: License :: OSI Approved :: MIT License
Classifier: Operating System :: OS Independent
Classifier: Programming Language :: Python :: 3
Classifier: Programming Language :: Python :: 3.10
Classifier: Programming Language :: Python :: 3.11
Classifier: Programming Language :: Python :: 3.12
Classifier: Programming Language :: Python :: 3.13
Classifier: Topic :: Office/Business :: Financial :: Investment
Classifier: Topic :: Software Development :: Libraries :: Python Modules
Classifier: Typing :: Typed
Requires-Python: >=3.10
Requires-Dist: beautifulsoup4>=4.12.0
Requires-Dist: httpx>=0.24.0
Requires-Dist: lxml>=4.9.0
Requires-Dist: numpy>=1.24.0
Requires-Dist: pandas>=2.0.0
Requires-Dist: pydantic>=2.0.0
Requires-Dist: requests>=2.28.0
Requires-Dist: tenacity>=8.2.0
Requires-Dist: tqdm>=4.65.0
Provides-Extra: async
Requires-Dist: aiocache>=0.12.0; extra == 'async'
Requires-Dist: aiohttp>=3.8.0; extra == 'async'
Provides-Extra: cache
Requires-Dist: diskcache>=5.6.0; extra == 'cache'
Requires-Dist: redis>=4.5.0; extra == 'cache'
Provides-Extra: dev
Requires-Dist: mypy>=1.3.0; extra == 'dev'
Requires-Dist: pre-commit>=3.3.0; extra == 'dev'
Requires-Dist: pytest-asyncio>=0.21.0; extra == 'dev'
Requires-Dist: pytest-cov>=4.1.0; extra == 'dev'
Requires-Dist: pytest>=7.3.0; extra == 'dev'
Requires-Dist: ruff>=0.1.0; extra == 'dev'
Provides-Extra: docs
Requires-Dist: mkdocs-material>=9.1.0; extra == 'docs'
Requires-Dist: mkdocs-static-i18n>=1.0.0; extra == 'docs'
Requires-Dist: mkdocs>=1.5.0; extra == 'docs'
Requires-Dist: mkdocstrings[python]>=0.22.0; extra == 'docs'
Provides-Extra: full
Requires-Dist: curl-cffi>=0.5.0; extra == 'full'
Requires-Dist: openpyxl>=3.1.0; extra == 'full'
Requires-Dist: xlrd>=2.0.0; extra == 'full'
